decayshape/__init__.py
decayshape/base.py
decayshape/config.py
decayshape/kmatrix_advanced.py
decayshape/lineshapes.py
decayshape/particles.py
decayshape/schema_utils.py
decayshape/utils.py
decayshape-0.2.6.dist-info/METADATA
decayshape-0.2.6.dist-info/WHEEL
decayshape-0.2.6.dist-info/licenses/LICENSE
decayshape-0.2.6.dist-info/RECORD
